README.md
setup.cfg
setup.py
anyseed/__init__.py
anyseed/anyseed.py
anyseed/bip39.py
anyseed/electrum.py
anyseed/old_mnemonic.py
anyseed/tools.py
anyseed/wordlist.py
anyseed.egg-info/PKG-INFO
anyseed.egg-info/SOURCES.txt
anyseed.egg-info/dependency_links.txt
anyseed.egg-info/not-zip-safe
anyseed.egg-info/top_level.txt
anyseed/bip39_wordlist/chinese_simplified.txt
anyseed/bip39_wordlist/chinese_traditional.txt
anyseed/bip39_wordlist/czech.txt
anyseed/bip39_wordlist/english.txt
anyseed/bip39_wordlist/french.txt
anyseed/bip39_wordlist/italian.txt
anyseed/bip39_wordlist/japanese.txt
anyseed/bip39_wordlist/korean.txt
anyseed/bip39_wordlist/portuguese.txt
anyseed/bip39_wordlist/spanish.txt
anyseed/electrum_wordlist/chinese_simplified.txt
anyseed/electrum_wordlist/english.txt
anyseed/electrum_wordlist/japanese.txt
anyseed/electrum_wordlist/portuguese.txt
anyseed/electrum_wordlist/spanish.txt