Metadata-Version: 1.0
Name: anyseed
Version: 1.1
Summary: Generating Seed from any mnemonic phrase
Home-page: UNKNOWN
Author: UNKNOWN
Author-email: phoenixburton@yandex.ru
License: UNKNOWN
Platform: UNKNOWN
